LICENSE
MANIFEST.in
README.rst
flask_oauthprovider.py
setup.py
flask_oauthprovider.egg-info/PKG-INFO
flask_oauthprovider.egg-info/SOURCES.txt
flask_oauthprovider.egg-info/dependency_links.txt
flask_oauthprovider.egg-info/not-zip-safe
flask_oauthprovider.egg-info/requires.txt
flask_oauthprovider.egg-info/top_level.txt