Metadata-Version: 1.0
Name: flask-oauthprovider
Version: 0.1.3
Summary: A full featured and secure OAuth provider base
Home-page: https://github.com/ib-lundgren/flask-oauthprovider
Author: Ib Lundgren
Author-email: ib.lundgren@gmail.com
License: Copyright (c) 2010-2011, Ib Lundgren and contributors.
